{"data":[{"id":"solana_B5K3qfft5ALRJBskL7qJPDzbbW76TXLkfKSd1mP4MtgN","type":"pool","attributes":{"base_token_price_usd":"0.0101583715926671702532813384854482071138817184975531974248001035","base_token_price_native_currency":"0.000122443588105939","quote_token_price_usd":"83.627462589321917829300611915607925781461308969","quote_token_price_native_currency":"1.0","base_token_price_quote_token":"0.0001224435881","quote_token_price_base_token":"8167.026264657","address":"B5K3qfft5ALRJBskL7qJPDzbbW76TXLkfKSd1mP4MtgN","name":"SCAM / SOL","pool_created_at":"2026-04-27T16:30:38Z","fdv_usd":"10178615.16","market_cap_usd":null,"price_change_percentage":{"m5":"3.9","m15":"-7.159","m30":"-9.075","h1":"-6.14","h6":"-15.664","h24":"29158.77"},"transactions":{"m5":{"buys":51,"sells":45,"buyers":39,"sellers":38},"m15":{"buys":521,"sells":261,"buyers":205,"sellers":164},"m30":{"buys":778,"sells":571,"buyers":293,"sellers":286},"h1":{"buys":1677,"sells":1509,"buyers":652,"sellers":676},"h6":{"buys":11127,"sells":9370,"buyers":2933,"sellers":2814},"h24":{"buys":119701,"sells":112195,"buyers":19462,"sellers":15780}},"volume_usd":{"m5":"11272.4331021032","m15":"96790.767014337","m30":"148005.634936813","h1":"404576.820828578","h6":"2783942.51368011","h24":"30948557.1472057"},"reserve_in_usd":"343525.3921"},"relationships":{"base_token":{"data":{"id":"solana_6AVAUKa9uxQpruHZUinFECpXEh1usRVtzQWK8N2wpump","type":"token"}},"quote_token":{"data":{"id":"solana_So11111111111111111111111111111111111111112","type":"token"}},"dex":{"data":{"id":"pumpswap","type":"dex"}}}},{"id":"solana_D2g8AAUqBzLpX7mxp6yg8v3Psau6hVc2dRLqjuaQXZyP","type":"pool","attributes":{"base_token_price_usd":"0.000687571387387993993360218516058338872347126596808508425027360752","base_token_price_native_currency":"0.00000819053272008327","quote_token_price_usd":"83.647545375758408140187783201969278160019208632","quote_token_price_native_currency":"1.0","base_token_price_quote_token":"0.00000819053272","quote_token_price_base_token":"122092.180591378","address":"D2g8AAUqBzLpX7mxp6yg8v3Psau6hVc2dRLqjuaQXZyP","name":"MASCOTS / SOL","pool_created_at":"2026-04-24T05:11:41Z","fdv_usd":"685093.7745","market_cap_usd":null,"price_change_percentage":{"m5":"-0.394","m15":"-4.294","m30":"-4.432","h1":"9.722","h6":"14.186","h24":"73.086"},"transactions":{"m5":{"buys":20,"sells":9,"buyers":20,"sellers":9},"m15":{"buys":105,"sells":70,"buyers":102,"sellers":68},"m30":{"buys":258,"sells":171,"buyers":243,"sellers":163},"h1":{"buys":5127,"sells":309,"buyers":5065,"sellers":247},"h6":{"buys":5429,"sells":497,"buyers":5222,"sellers":355},"h24":{"buys":21474,"sells":8841,"buyers":10523,"sellers":2847}},"volume_usd":{"m5":"1165.6514152973","m15":"6193.0787600525","m30":"23075.8816703519","h1":"43825.3198114872","h6":"69742.967023824","h24":"1030794.03894281"},"reserve_in_usd":"73621.4433"},"relationships":{"base_token":{"data":{"id":"solana_8GxLxKA8tf3h8JUkXFfP4dNyn6D2vvwyGif5wanRpump","type":"token"}},"quote_token":{"data":{"id":"solana_So11111111111111111111111111111111111111112","type":"token"}},"dex":{"data":{"id":"pumpswap","type":"dex"}}}},{"id":"solana_5JSMSd7NSp2iLZNAJo9H2oewxEewqphR1skL65F9Uywt","type":"pool","attributes":{"base_token_price_usd":"0.000260246091314240723723494783780260404486086575298436455837002024","base_token_price_native_currency":"0.00000306549394724679","quote_token_price_usd":"83.647545375758408140187783201969278160019208632","quote_token_price_native_currency":"1.0","base_token_price_quote_token":"0.000003065493947","quote_token_price_base_token":"326211.702651747","address":"5JSMSd7NSp2iLZNAJo9H2oewxEewqphR1skL65F9Uywt","name":"HENRY / SOL","pool_created_at":"2026-04-26T03:18:00Z","fdv_usd":"259086.21200562","market_cap_usd":"259086.402257889","price_change_percentage":{"m5":"-0.755","m15":"0.009","m30":"-0.137","h1":"-1.567","h6":"-19.048","h24":"-86.379"},"transactions":{"m5":{"buys":7,"sells":6,"buyers":6,"sellers":6},"m15":{"buys":21,"sells":23,"buyers":18,"sellers":22},"m30":{"buys":56,"sells":70,"buyers":42,"sellers":60},"h1":{"buys":201,"sells":152,"buyers":118,"sellers":106},"h6":{"buys":1369,"sells":1291,"buyers":500,"sellers":538},"h24":{"buys":15880,"sells":13526,"buyers":3103,"sellers":4383}},"volume_usd":{"m5":"599.9273333104","m15":"1946.5282741644","m30":"4564.4105055477","h1":"15191.5943079433","h6":"139097.864003816","h24":"1921217.05732773"},"reserve_in_usd":"56996.8984"},"relationships":{"base_token":{"data":{"id":"solana_CJUrENDAuSm4FxxziUgftnUJqqXjm4VL1zhJgwXupump","type":"token"}},"quote_token":{"data":{"id":"solana_So11111111111111111111111111111111111111112","type":"token"}},"dex":{"data":{"id":"pumpswap","type":"dex"}}}},{"id":"solana_8Nz7G5N4GuZj9cYCEJvV1YNzx5ENK9FJXjMjhaDcawMV","type":"pool","attributes":{"base_token_price_usd":"0.000317414574804261862108464990342528638229480973140634898886356957","base_token_price_native_currency":"0.0000037972687654571","quote_token_price_usd":"83.627217582664220002061999326370202370006909769","quote_token_price_native_currency":"1.0","base_token_price_quote_token":"0.000003797268765","quote_token_price_base_token":"263347.17444727","address":"8Nz7G5N4GuZj9cYCEJvV1YNzx5ENK9FJXjMjhaDcawMV","name":"STOCKMAN / SOL","pool_created_at":"2026-04-27T16:50:23Z","fdv_usd":"317629.0215","market_cap_usd":null,"price_change_percentage":{"m5":"-0.62","m15":"8.888","m30":"-11.287","h1":"-14.393","h6":"2.83","h24":"802.979"},"transactions":{"m5":{"buys":7,"sells":10,"buyers":6,"sellers":10},"m15":{"buys":73,"sells":84,"buyers":52,"sellers":71},"m30":{"buys":184,"sells":173,"buyers":111,"sellers":140},"h1":{"buys":299,"sells":297,"buyers":180,"sellers":219},"h6":{"buys":2586,"sells":2165,"buyers":963,"sellers":984},"h24":{"buys":37030,"sells":29666,"buyers":7735,"sellers":6750}},"volume_usd":{"m5":"847.6377364466","m15":"12459.1607416274","m30":"28385.1330081293","h1":"42498.5324251963","h6":"287954.60468499","h24":"4736451.81728295"},"reserve_in_usd":"53940.1432"},"relationships":{"base_token":{"data":{"id":"solana_5nrLD7JDem6LiJNRP43NjLAkE8WFc2WZYZafBW42smqf","type":"token"}},"quote_token":{"data":{"id":"solana_So11111111111111111111111111111111111111112","type":"token"}},"dex":{"data":{"id":"pumpswap","type":"dex"}}}},{"id":"solana_HT8ZEh6PdSkB6HTXjqiKMQhNwZY6mqjmW57mF3r9wHfW","type":"pool","attributes":{"base_token_price_usd":"0.000402132947662224475307576035696250067900150080488918225441610854","base_token_price_native_currency":"0.00000486877617552743","quote_token_price_usd":"83.647313336337202912085130695777477926500400223","quote_token_price_native_currency":"1.0","base_token_price_quote_token":"0.000004868776176","quote_token_price_base_token":"205390.423373009","address":"HT8ZEh6PdSkB6HTXjqiKMQhNwZY6mqjmW57mF3r9wHfW","name":"SCAM / SOL","pool_created_at":"2026-04-27T17:14:11Z","fdv_usd":"401998.067497068","market_cap_usd":null,"price_change_percentage":{"m5":"0.196","m15":"5.356","m30":"-1.319","h1":"26.175","h6":"2.348","h24":"1120.411"},"transactions":{"m5":{"buys":7,"sells":10,"buyers":6,"sellers":10},"m15":{"buys":37,"sells":34,"buyers":33,"sellers":32},"m30":{"buys":145,"sells":125,"buyers":90,"sellers":96},"h1":{"buys":269,"sells":253,"buyers":167,"sellers":190},"h6":{"buys":2409,"sells":2188,"buyers":925,"sellers":942},"h24":{"buys":24298,"sells":20459,"buyers":5336,"sellers":4829}},"volume_usd":{"m5":"1217.1405852637","m15":"5988.6758302052","m30":"35889.4914323757","h1":"61181.5918796042","h6":"360749.229998529","h24":"4139579.22881665"},"reserve_in_usd":"57126.4816"},"relationships":{"base_token":{"data":{"id":"solana_DXcwhg1MwrResr1CoaBuhnnHmcx222ntZAgRd28Jpump","type":"token"}},"quote_token":{"data":{"id":"solana_So11111111111111111111111111111111111111112","type":"token"}},"dex":{"data":{"id":"pumpswap","type":"dex"}}}},{"id":"solana_24BiS4cYDTLAGJFEDhNcBowXma3YxXmWYcCbxVKPPcUy","type":"pool","attributes":{"base_token_price_usd":"0.000088282201292148465385556942374266516961706022566330174938845726","base_token_price_native_currency":"0.00000101636807585631","quote_token_price_usd":"83.641939632451613885433099662363655353765080182","quote_token_price_native_currency":"1.0","base_token_price_quote_token":"0.000001016368076","quote_token_price_base_token":"983895.523437688","address":"24BiS4cYDTLAGJFEDhNcBowXma3YxXmWYcCbxVKPPcUy","name":"ANNIE / SOL","pool_created_at":"2026-04-28T02:16:50Z","fdv_usd":"85031.13999","market_cap_usd":null,"price_change_percentage":{"m5":"-6.294","m15":"-1.663","m30":"-16.034","h1":"-1.026","h6":"102.559","h24":"140.684"},"transactions":{"m5":{"buys":10,"sells":8,"buyers":9,"sellers":8},"m15":{"buys":67,"sells":47,"buyers":47,"sellers":41},"m30":{"buys":137,"sells":107,"buyers":95,"sellers":85},"h1":{"buys":365,"sells":268,"buyers":221,"sellers":183},"h6":{"buys":3028,"sells":2376,"buyers":1306,"sellers":1129},"h24":{"buys":20471,"sells":15861,"buyers":5540,"sellers":4739}},"volume_usd":{"m5":"436.3856467854","m15":"4519.7853841951","m30":"10440.5096795012","h1":"24811.7317204122","h6":"219386.312369067","h24":"1968553.21686974"},"reserve_in_usd":"25629.5369"},"relationships":{"base_token":{"data":{"id":"solana_DCNEi1eFWEFA7MQYkh8kSDeZ3bgja453j1sQ3Rn1pump","type":"token"}},"quote_token":{"data":{"id":"solana_So11111111111111111111111111111111111111112","type":"token"}},"dex":{"data":{"id":"pumpswap","type":"dex"}}}},{"id":"solana_Hxw77h9fEx598afiiZunwHaX3vYu9UskDk9EpPNZp1mG","type":"pool","attributes":{"base_token_price_usd":"1.70731586527353498411592644818108858445535332","base_token_price_native_currency":"0.0203879223227753","quote_token_price_usd":"83.787216685360972309785607188","quote_token_price_native_currency":"1.0","base_token_price_quote_token":"0.02038792232","quote_token_price_base_token":"49.048646751","address":"Hxw77h9fEx598afiiZunwHaX3vYu9UskDk9EpPNZp1mG","name":"ORCA / SOL","pool_created_at":"2024-01-04T20:53:02Z","fdv_usd":"128120268.981078","market_cap_usd":"103861376.125417","price_change_percentage":{"m5":"-1.424","m15":"-2.561","m30":"-4.254","h1":"1.346","h6":"13.442","h24":"40.213"},"transactions":{"m5":{"buys":561,"sells":183,"buyers":65,"sellers":10},"m15":{"buys":774,"sells":344,"buyers":80,"sellers":20},"m30":{"buys":2156,"sells":1069,"buyers":115,"sellers":79},"h1":{"buys":4806,"sells":6078,"buyers":161,"sellers":158},"h6":{"buys":15224,"sells":20785,"buyers":329,"sellers":285},"h24":{"buys":95882,"sells":112905,"buyers":833,"sellers":773}},"volume_usd":{"m5":"51040.5062212329","m15":"125682.136698512","m30":"360240.447456403","h1":"1063927.40712097","h6":"4057741.91574202","h24":"21090894.1212205"},"reserve_in_usd":"960083.6083"},"relationships":{"base_token":{"data":{"id":"solana_orcaEKTdK7LKz57vaAYr9QeNsVEPfiu6QeMU1kektZE","type":"token"}},"quote_token":{"data":{"id":"solana_So11111111111111111111111111111111111111112","type":"token"}},"dex":{"data":{"id":"orca","type":"dex"}}}},{"id":"solana_2RMm8BoXPAMwuLwouAcxJym5rAra5FsuGc3Fe4k76qJ8","type":"pool","attributes":{"base_token_price_usd":"0.0014680648853114351025022078736041784677346144164116943716926185","base_token_price_native_currency":"0.0000179583666873536","quote_token_price_usd":"83.64689100346744480908298594873236209175766999","quote_token_price_native_currency":"1.0","base_token_price_quote_token":"0.00001795836669","quote_token_price_base_token":"55684.3513338107","address":"2RMm8BoXPAMwuLwouAcxJym5rAra5FsuGc3Fe4k76qJ8","name":"BELKA / SOL","pool_created_at":"2026-04-24T22:42:45Z","fdv_usd":"1503620.58059727","market_cap_usd":"1503620.64005874","price_change_percentage":{"m5":"0.152","m15":"2.338","m30":"-1.578","h1":"-6.433","h6":"12.026","h24":"-52.821"},"transactions":{"m5":{"buys":2,"sells":4,"buyers":2,"sellers":4},"m15":{"buys":34,"sells":33,"buyers":24,"sellers":30},"m30":{"buys":99,"sells":66,"buyers":67,"sellers":61},"h1":{"buys":260,"sells":182,"buyers":160,"sellers":157},"h6":{"buys":1314,"sells":1147,"buyers":662,"sellers":719},"h24":{"buys":11380,"sells":10488,"buyers":3233,"sellers":3447}},"volume_usd":{"m5":"312.1468099801","m15":"7289.7014851557","m30":"17948.5905071291","h1":"49123.8581749009","h6":"271102.108552668","h24":"2473617.17209916"},"reserve_in_usd":"114283.106"},"relationships":{"base_token":{"data":{"id":"solana_4df1wZoygsynEZ6XmpcoabrVwv7nBgjHLyCns5xApump","type":"token"}},"quote_token":{"data":{"id":"solana_So11111111111111111111111111111111111111112","type":"token"}},"dex":{"data":{"id":"pumpswap","type":"dex"}}}},{"id":"solana_5tYFviFWQRKV9BJSTHGitbdqEYC1BGUgRUDnSADUXqJP","type":"pool","attributes":{"base_token_price_usd":"0.012587252911844698024335448040989325865023727007125239896908438","base_token_price_native_currency":"0.000147895858554045","quote_token_price_usd":"83.661757984262188744759110750735523072231023099","quote_token_price_native_currency":"1.0","base_token_price_quote_token":"0.0001478958586","quote_token_price_base_token":"6761.514553395","address":"5tYFviFWQRKV9BJSTHGitbdqEYC1BGUgRUDnSADUXqJP","name":"BURNIE / SOL","pool_created_at":"2026-04-03T03:08:37Z","fdv_usd":"12209259.6179417","market_cap_usd":"12209259.6179417","price_change_percentage":{"m5":"2.091","m15":"-0.659","m30":"6.7","h1":"2.06","h6":"-1.92","h24":"-20.987"},"transactions":{"m5":{"buys":5,"sells":6,"buyers":4,"sellers":6},"m15":{"buys":30,"sells":64,"buyers":21,"sellers":50},"m30":{"buys":65,"sells":132,"buyers":47,"sellers":78},"h1":{"buys":231,"sells":180,"buyers":147,"sellers":113},"h6":{"buys":853,"sells":864,"buyers":417,"sellers":441},"h24":{"buys":9003,"sells":7888,"buyers":2056,"sellers":2243}},"volume_usd":{"m5":"5048.9483534438","m15":"17760.8367883439","m30":"33630.663123165","h1":"73266.0893693344","h6":"355554.829173945","h24":"3377356.64999569"},"reserve_in_usd":"452223.7584"},"relationships":{"base_token":{"data":{"id":"solana_CGEDT9QZDvvH5GmVkWJH2BXiMJqMJySC9ihWyr7Spump","type":"token"}},"quote_token":{"data":{"id":"solana_So11111111111111111111111111111111111111112","type":"token"}},"dex":{"data":{"id":"pumpswap","type":"dex"}}}},{"id":"solana_Dt6EtrQcXjGPy9Rdw77Rf7WVxJ9FH6dxTpRYdUQ3GDNg","type":"pool","attributes":{"base_token_price_usd":"0.000509344580007523892510519847432944649496087899406393339960868544","base_token_price_native_currency":"0.00000612675954757137","quote_token_price_usd":"83.726972279464479005858797669187033988468226188","quote_token_price_native_currency":"1.0","base_token_price_quote_token":"0.000006126759548","quote_token_price_base_token":"163218.417865998","address":"Dt6EtrQcXjGPy9Rdw77Rf7WVxJ9FH6dxTpRYdUQ3GDNg","name":"SAM / SOL","pool_created_at":"2026-04-23T01:14:17Z","fdv_usd":"509053.917937499","market_cap_usd":"509053.918269583","price_change_percentage":{"m5":"-0.713","m15":"-0.116","m30":"-2.737","h1":"1.874","h6":"21.787","h24":"-62.084"},"transactions":{"m5":{"buys":0,"sells":2,"buyers":0,"sellers":2},"m15":{"buys":17,"sells":23,"buyers":11,"sellers":12},"m30":{"buys":27,"sells":40,"buyers":19,"sellers":29},"h1":{"buys":79,"sells":72,"buyers":55,"sellers":53},"h6":{"buys":620,"sells":605,"buyers":338,"sellers":374},"h24":{"buys":7057,"sells":6043,"buyers":2024,"sellers":2430}},"volume_usd":{"m5":"286.7582443357","m15":"1122.1526816453","m30":"2780.4972933463","h1":"8689.5831918426","h6":"137988.901261883","h24":"1295297.02561938"},"reserve_in_usd":"81369.7792"},"relationships":{"base_token":{"data":{"id":"solana_7WRX5QGuRLhGCJszpQjYmw6ihb6z8KRdAEHQUhGJpump","type":"token"}},"quote_token":{"data":{"id":"solana_So11111111111111111111111111111111111111112","type":"token"}},"dex":{"data":{"id":"pumpswap","type":"dex"}}}},{"id":"solana_HVimk99ygSSDnWz9eSqumdThrFz4DADE7j6phmFms6at","type":"pool","attributes":{"base_token_price_usd":"0.0159343749851030139985493901375142842845437391139218966938879968","base_token_price_native_currency":"0.000191427910131197","quote_token_price_usd":"83.661757984262188744759110750735523072231023099","quote_token_price_native_currency":"1.0","base_token_price_quote_token":"0.0001914279101","quote_token_price_base_token":"5223.898643174","address":"HVimk99ygSSDnWz9eSqumdThrFz4DADE7j6phmFms6at","name":"MAGA / SOL","pool_created_at":"2026-02-20T22:02:46Z","fdv_usd":"15676993.1957895","market_cap_usd":"15676994.3566099","price_change_percentage":{"m5":"1.367","m15":"1.677","m30":"2.579","h1":"-3.914","h6":"-6.497","h24":"-1.858"},"transactions":{"m5":{"buys":3,"sells":3,"buyers":3,"sellers":3},"m15":{"buys":11,"sells":10,"buyers":11,"sellers":9},"m30":{"buys":32,"sells":18,"buyers":25,"sellers":17},"h1":{"buys":81,"sells":56,"buyers":48,"sellers":49},"h6":{"buys":453,"sells":482,"buyers":248,"sellers":344},"h24":{"buys":5441,"sells":5283,"buyers":1824,"sellers":1957}},"volume_usd":{"m5":"1451.679073371","m15":"3733.3337431229","m30":"7635.071207707","h1":"17411.2765460311","h6":"125275.065562472","h24":"2193360.45030877"},"reserve_in_usd":"413767.704"},"relationships":{"base_token":{"data":{"id":"solana_Hon2rHAiqkcDtUzL5gA2vjXPr7T1MPCK2UT2AHKCpump","type":"token"}},"quote_token":{"data":{"id":"solana_So11111111111111111111111111111111111111112","type":"token"}},"dex":{"data":{"id":"pumpswap","type":"dex"}}}},{"id":"solana_7HU7JmtphKSSG6w5z4bykdEwHqF3Z4vDRchRZJDJnAyx","type":"pool","attributes":{"base_token_price_usd":"0.0002426335632734757697977567997543133001196232986200208707","base_token_price_native_currency":"0.0000029136975627941","quote_token_price_usd":"83.661757984662145418211721016465363192526658883","quote_token_price_native_currency":"1.0","base_token_price_quote_token":"0.000002913697563","quote_token_price_base_token":"343206.51970517","address":"7HU7JmtphKSSG6w5z4bykdEwHqF3Z4vDRchRZJDJnAyx","name":"Dunald / SOL","pool_created_at":"2026-04-25T13:26:43Z","fdv_usd":"242626.387516758","market_cap_usd":"232758.083093475","price_change_percentage":{"m5":"-0.02","m15":"-2.951","m30":"-11.032","h1":"-17.278","h6":"12.683","h24":"-48.311"},"transactions":{"m5":{"buys":2,"sells":3,"buyers":2,"sellers":3},"m15":{"buys":35,"sells":36,"buyers":30,"sellers":27},"m30":{"buys":61,"sells":58,"buyers":49,"sellers":42},"h1":{"buys":114,"sells":110,"buyers":71,"sellers":79},"h6":{"buys":586,"sells":553,"buyers":268,"sellers":321},"h24":{"buys":6310,"sells":5256,"buyers":1722,"sellers":1948}},"volume_usd":{"m5":"399.904038053","m15":"3568.3236667152","m30":"6873.8715912379","h1":"13819.7158525775","h6":"65568.9019739362","h24":"812060.040361377"},"reserve_in_usd":"47076.7449"},"relationships":{"base_token":{"data":{"id":"solana_3hPjuKcU2Bs2hGnwrkNnYFnmkUbJNsaPpM6MzRH7pump","type":"token"}},"quote_token":{"data":{"id":"solana_So11111111111111111111111111111111111111112","type":"token"}},"dex":{"data":{"id":"pumpswap","type":"dex"}}}},{"id":"solana_5KekXEFytdbrkvERNNNGxVFovevYJxukKc7iGUwy873K","type":"pool","attributes":{"base_token_price_usd":"0.00011771128569396837617575971570359922244510701108618500023107036","base_token_price_native_currency":"0.00000138877152335977","quote_token_price_usd":"83.646705344837127226572851072287791639381365388","quote_token_price_native_currency":"1.0","base_token_price_quote_token":"0.000001388771523","quote_token_price_base_token":"720060.847432097","address":"5KekXEFytdbrkvERNNNGxVFovevYJxukKc7iGUwy873K","name":"NICE / SOL","pool_created_at":"2026-02-17T19:04:18Z","fdv_usd":"116122.431979427","market_cap_usd":"116122.431979427","price_change_percentage":{"m5":"8.443","m15":"0.776","m30":"13.308","h1":"3.09","h6":"-40.727","h24":"98.724"},"transactions":{"m5":{"buys":6,"sells":6,"buyers":5,"sellers":6},"m15":{"buys":18,"sells":30,"buyers":17,"sellers":28},"m30":{"buys":54,"sells":71,"buyers":41,"sellers":64},"h1":{"buys":156,"sells":197,"buyers":121,"sellers":143},"h6":{"buys":790,"sells":653,"buyers":434,"sellers":404},"h24":{"buys":12467,"sells":9612,"buyers":5972,"sellers":4117}},"volume_usd":{"m5":"1759.0828174207","m15":"2853.5683919577","m30":"5745.0837125151","h1":"15646.5448072071","h6":"68440.8530314046","h24":"1107324.21983773"},"reserve_in_usd":"30709.983"},"relationships":{"base_token":{"data":{"id":"solana_7fj85y28pKMndm4So66Szkb5GMGfLHFEkwsZdDx2pump","type":"token"}},"quote_token":{"data":{"id":"solana_So11111111111111111111111111111111111111112","type":"token"}},"dex":{"data":{"id":"pumpswap","type":"dex"}}}},{"id":"solana_Dx5wFoszXvND6XYYAjAjUQrGLqDAUrTVH2JmHz6eJDNt","type":"pool","attributes":{"base_token_price_usd":"0.00257471904973047705260038709341162226690316629855667461698581033","base_token_price_native_currency":"0.0000310843158625245","quote_token_price_usd":"83.626913156696197898088871440577423847623875753","quote_token_price_native_currency":"1.0","base_token_price_quote_token":"0.00003108431586","quote_token_price_base_token":"32170.5648733807","address":"Dx5wFoszXvND6XYYAjAjUQrGLqDAUrTVH2JmHz6eJDNt","name":"LOL / SOL","pool_created_at":"2026-03-18T23:57:45Z","fdv_usd":"2550881.58656919","market_cap_usd":"2550890.46191143","price_change_percentage":{"m5":"-0.966","m15":"-0.344","m30":"2.217","h1":"0.771","h6":"9.481","h24":"-10.316"},"transactions":{"m5":{"buys":17,"sells":15,"buyers":16,"sellers":15},"m15":{"buys":100,"sells":91,"buyers":92,"sellers":89},"m30":{"buys":234,"sells":212,"buyers":216,"sellers":205},"h1":{"buys":482,"sells":450,"buyers":449,"sellers":438},"h6":{"buys":3768,"sells":3535,"buyers":3627,"sellers":3385},"h24":{"buys":14633,"sells":13768,"buyers":13519,"sellers":12581}},"volume_usd":{"m5":"209.0552825965","m15":"721.174899803","m30":"1627.0488106746","h1":"5692.2641191789","h6":"201069.426164727","h24":"952461.528451034"},"reserve_in_usd":"255591.2804"},"relationships":{"base_token":{"data":{"id":"solana_34q2KmCvapecJgR6ZrtbCTrzZVtkt3a5mHEA3TuEsWYb","type":"token"}},"quote_token":{"data":{"id":"solana_So11111111111111111111111111111111111111112","type":"token"}},"dex":{"data":{"id":"pumpswap","type":"dex"}}}},{"id":"solana_9rNWPkDD5dLnujmqR5d7jiDuNEWZiXGADZdxbBUocBi1","type":"pool","attributes":{"base_token_price_usd":"0.000550008173862813286859613110762456327857256556381132231421749277","base_token_price_native_currency":"0.00000652283369474187","quote_token_price_usd":"83.627217582664220002061999326370202370006909769","quote_token_price_native_currency":"1.0","base_token_price_quote_token":"0.000006522833695","quote_token_price_base_token":"153307.603228657","address":"9rNWPkDD5dLnujmqR5d7jiDuNEWZiXGADZdxbBUocBi1","name":"LUCA / SOL","pool_created_at":"2026-04-28T05:43:39Z","fdv_usd":"543720.034316588","market_cap_usd":null,"price_change_percentage":{"m5":"9.823","m15":"17.835","m30":"31.984","h1":"53.707","h6":"59.236","h24":"1572.005"},"transactions":{"m5":{"buys":46,"sells":43,"buyers":42,"sellers":37},"m15":{"buys":180,"sells":180,"buyers":136,"sellers":137},"m30":{"buys":400,"sells":357,"buyers":263,"sellers":251},"h1":{"buys":1129,"sells":993,"buyers":573,"sellers":538},"h6":{"buys":10089,"sells":8109,"buyers":3009,"sellers":2899},"h24":{"buys":33138,"sells":30558,"buyers":7359,"sellers":6482}},"volume_usd":{"m5":"5445.2795751325","m15":"28244.6103186002","m30":"61060.7624433569","h1":"173864.026100422","h6":"1211020.78520033","h24":"4587583.84657647"},"reserve_in_usd":"68096.4795"},"relationships":{"base_token":{"data":{"id":"solana_BZ1avfKCfJKNgsDeXHNkPku5GcWVzi2Aw2HesHcrpump","type":"token"}},"quote_token":{"data":{"id":"solana_So11111111111111111111111111111111111111112","type":"token"}},"dex":{"data":{"id":"pumpswap","type":"dex"}}}},{"id":"solana_HnhpJPJgBG2KwniMTNW8cVBHvk1hFog3RC3kjnyc23tD","type":"pool","attributes":{"base_token_price_usd":"0.081272950822516319202198525348832365155888194","base_token_price_native_currency":"0.000969719893216012","quote_token_price_usd":"1.001352327423183283337544335520151095881122","quote_token_price_native_currency":"0.0119479436399299","base_token_price_quote_token":"0.08116207462","quote_token_price_base_token":"12.3210256111","address":"HnhpJPJgBG2KwniMTNW8cVBHvk1hFog3RC3kjnyc23tD","name":"CARDS / USDC","pool_created_at":"2025-08-29T18:54:46Z","fdv_usd":"162522022.762604","market_cap_usd":"20932029.7718937","price_change_percentage":{"m5":"0.652","m15":"-1.595","m30":"-1.251","h1":"1.207","h6":"3.964","h24":"-23.314"},"transactions":{"m5":{"buys":6,"sells":3,"buyers":2,"sellers":3},"m15":{"buys":20,"sells":14,"buyers":4,"sellers":11},"m30":{"buys":26,"sells":24,"buyers":7,"sellers":17},"h1":{"buys":91,"sells":72,"buyers":21,"sellers":34},"h6":{"buys":573,"sells":458,"buyers":122,"sellers":138},"h24":{"buys":3694,"sells":3075,"buyers":551,"sellers":525}},"volume_usd":{"m5":"1271.7035150433","m15":"13395.5678529597","m30":"21719.0213873503","h1":"46898.0752931092","h6":"229407.581919179","h24":"2174144.80902288"},"reserve_in_usd":"1174171.3382"},"relationships":{"base_token":{"data":{"id":"solana_CARDSccUMFKoPRZxt5vt3ksUbxEFEcnZ3H2pd3dKxYjp","type":"token"}},"quote_token":{"data":{"id":"solana_EPjFWdd5AufqSSqeM2qN1xzybapC8G4wEGGkZwyTDt1v","type":"token"}},"dex":{"data":{"id":"raydium-clmm","type":"dex"}}}},{"id":"solana_58xvayxZEuUSmENvRVgDdkSsUe6yFnevXBQBRppGatgj","type":"pool","attributes":{"base_token_price_usd":"0.00015219038378420785167833400149157807098381517315652206657775261","base_token_price_native_currency":"0.00000182412872038332","quote_token_price_usd":"83.663603326746331524371992424712076248254824165","quote_token_price_native_currency":"1.0","base_token_price_quote_token":"0.00000182412872","quote_token_price_base_token":"548206.926860875","address":"58xvayxZEuUSmENvRVgDdkSsUe6yFnevXBQBRppGatgj","name":"ClosedAI / SOL","pool_created_at":"2026-04-27T19:20:17Z","fdv_usd":"152190.3838","market_cap_usd":null,"price_change_percentage":{"m5":"-1.176","m15":"-9.22","m30":"-1.851","h1":"-4.029","h6":"55.16","h24":"326.716"},"transactions":{"m5":{"buys":2,"sells":4,"buyers":2,"sellers":4},"m15":{"buys":14,"sells":20,"buyers":12,"sellers":20},"m30":{"buys":55,"sells":50,"buyers":41,"sellers":45},"h1":{"buys":118,"sells":94,"buyers":82,"sellers":82},"h6":{"buys":1242,"sells":1011,"buyers":537,"sellers":591},"h24":{"buys":18573,"sells":14232,"buyers":4673,"sellers":4199}},"volume_usd":{"m5":"145.891531918","m15":"1706.0154526434","m30":"7698.5281896356","h1":"13079.2042164682","h6":"132061.450036402","h24":"2306938.52488549"},"reserve_in_usd":"33808.2668"},"relationships":{"base_token":{"data":{"id":"solana_2A3fFL8XcvLyx7AECNBdRwK2UEW9p5P9k52EtTBUpump","type":"token"}},"quote_token":{"data":{"id":"solana_So11111111111111111111111111111111111111112","type":"token"}},"dex":{"data":{"id":"pumpswap","type":"dex"}}}},{"id":"solana_FFXWfy7awwaQwZNM2fKrXipHeWd7DWGz4ryVsmghnqct","type":"pool","attributes":{"base_token_price_usd":"0.0000267226891600971606883354378844554399189438851196221093558694184","base_token_price_native_currency":"0.000000318139447812531","quote_token_price_usd":"83.626912986219865815807764469920670012639809588","quote_token_price_native_currency":"1.0","base_token_price_quote_token":"0.0000003181394478","quote_token_price_base_token":"3143275.71408016","address":"FFXWfy7awwaQwZNM2fKrXipHeWd7DWGz4ryVsmghnqct","name":"paranoid / SOL","pool_created_at":"2026-04-27T22:57:43Z","fdv_usd":"26664.82207","market_cap_usd":null,"price_change_percentage":{"m5":"2.716","m15":"4.99","m30":"3.659","h1":"-2.248","h6":"-38.976","h24":"-24.126"},"transactions":{"m5":{"buys":6,"sells":4,"buyers":6,"sellers":4},"m15":{"buys":31,"sells":12,"buyers":25,"sellers":12},"m30":{"buys":67,"sells":46,"buyers":52,"sellers":40},"h1":{"buys":105,"sells":89,"buyers":72,"sellers":74},"h6":{"buys":1054,"sells":959,"buyers":461,"sellers":577},"h24":{"buys":22043,"sells":17095,"buyers":4991,"sellers":4607}},"volume_usd":{"m5":"313.8267485099","m15":"938.9091075877","m30":"4183.1816723722","h1":"6289.7928884926","h6":"59418.7249564902","h24":"2300389.64847765"},"reserve_in_usd":"14513.4266"},"relationships":{"base_token":{"data":{"id":"solana_CUi5ULzTKY9P93cjkCVD8HrB6txw2v4yzQuwBJgipump","type":"token"}},"quote_token":{"data":{"id":"solana_So11111111111111111111111111111111111111112","type":"token"}},"dex":{"data":{"id":"pumpswap","type":"dex"}}}},{"id":"solana_HNGjLLZkWx2mNwhWdKFYcMowz8FTh2bXxdpJ1vBVkjNB","type":"pool","attributes":{"base_token_price_usd":"0.00479063660217775073302668150397236512092936490834060975093043971","base_token_price_native_currency":"0.0000568612529921918","quote_token_price_usd":"83.627217585183686309669364928435939580388064109","quote_token_price_native_currency":"1.0","base_token_price_quote_token":"0.00005686125299","quote_token_price_base_token":"17586.6683792093","address":"HNGjLLZkWx2mNwhWdKFYcMowz8FTh2bXxdpJ1vBVkjNB","name":"BULL / SOL","pool_created_at":"2026-03-23T15:02:43Z","fdv_usd":"4752152.30559437","market_cap_usd":"4752152.46226378","price_change_percentage":{"m5":"-0.405","m15":"-4.885","m30":"-9.528","h1":"2.129","h6":"25.215","h24":"19.653"},"transactions":{"m5":{"buys":23,"sells":19,"buyers":21,"sellers":17},"m15":{"buys":137,"sells":124,"buyers":90,"sellers":79},"m30":{"buys":314,"sells":302,"buyers":186,"sellers":167},"h1":{"buys":800,"sells":792,"buyers":355,"sellers":329},"h6":{"buys":3544,"sells":2543,"buyers":540,"sellers":565},"h24":{"buys":10392,"sells":9167,"buyers":1078,"sellers":1253}},"volume_usd":{"m5":"2301.7385121188","m15":"20230.628689592","m30":"67247.7825552811","h1":"202101.015001547","h6":"437541.878840035","h24":"1141039.41319731"},"reserve_in_usd":"271323.8907"},"relationships":{"base_token":{"data":{"id":"solana_3TYgKwkE2Y3rxdw9osLRSpxpXmSC1C1oo19W9KHspump","type":"token"}},"quote_token":{"data":{"id":"solana_So11111111111111111111111111111111111111112","type":"token"}},"dex":{"data":{"id":"pumpswap","type":"dex"}}}},{"id":"solana_5VXPSSnSxa2bP9HPdHXt9pCXVyfwXwRN8HRE2pyoN88M","type":"pool","attributes":{"base_token_price_usd":"0.00359563618892897249510717274374954460586726352092122117673388556","base_token_price_native_currency":"0.0000431387447425367","quote_token_price_usd":"1.0003451602404248659116167636904577602821758797771316914009858","quote_token_price_native_currency":"0.0119598512975219","base_token_price_quote_token":"0.003606963303","quote_token_price_base_token":"277.2415231111","address":"5VXPSSnSxa2bP9HPdHXt9pCXVyfwXwRN8HRE2pyoN88M","name":"ZBCN / USDC","pool_created_at":"2025-02-18T15:25:56Z","fdv_usd":"359562458.826244","market_cap_usd":"352201909.557159","price_change_percentage":{"m5":"0.402","m15":"0.385","m30":"1.072","h1":"-0.4","h6":"-1.781","h24":"-6.937"},"transactions":{"m5":{"buys":12,"sells":24,"buyers":4,"sellers":12},"m15":{"buys":25,"sells":58,"buyers":12,"sellers":20},"m30":{"buys":41,"sells":73,"buyers":20,"sellers":24},"h1":{"buys":196,"sells":137,"buyers":66,"sellers":36},"h6":{"buys":725,"sells":784,"buyers":186,"sellers":146},"h24":{"buys":4169,"sells":4508,"buyers":563,"sellers":506}},"volume_usd":{"m5":"2143.9591286406","m15":"5835.0730248367","m30":"7841.7239861331","h1":"18889.5820997137","h6":"128761.163608677","h24":"1026664.01722692"},"reserve_in_usd":"72487.3519"},"relationships":{"base_token":{"data":{"id":"solana_ZBCNpuD7YMXzTHB2fhGkGi78MNsHGLRXUhRewNRm9RU","type":"token"}},"quote_token":{"data":{"id":"solana_EPjFWdd5AufqSSqeM2qN1xzybapC8G4wEGGkZwyTDt1v","type":"token"}},"dex":{"data":{"id":"meteora","type":"dex"}}}}]}