{"data":[{"id":"bsc_0x3193d3f5ebe4ef6725f131d5610eb9b67b25f0e6","type":"pool","attributes":{"base_token_price_usd":"0.0943835393696686","base_token_price_native_currency":"0.000154844323091017","quote_token_price_usd":"0.997640573893815","quote_token_price_native_currency":"0.00159991111343546","base_token_price_quote_token":"0.09678307863","quote_token_price_base_token":"10.3323846913","address":"0x3193d3f5ebe4ef6725f131d5610eb9b67b25f0e6","name":"AI / USDT","pool_created_at":"2026-04-29T09:15:17Z","fdv_usd":"87266507.12","market_cap_usd":null,"price_change_percentage":{"m5":"-28.255","m15":"2.867","m30":"16.8","h1":"8.813","h6":"346759.635","h24":"346759.635"},"transactions":{"m5":{"buys":17,"sells":28,"buyers":17,"sellers":28},"m15":{"buys":69,"sells":63,"buyers":69,"sellers":63},"m30":{"buys":135,"sells":129,"buyers":135,"sellers":129},"h1":{"buys":264,"sells":261,"buyers":264,"sellers":261},"h6":{"buys":1495,"sells":1428,"buyers":1266,"sellers":1199},"h24":{"buys":1495,"sells":1428,"buyers":1266,"sellers":1199}},"volume_usd":{"m5":"698620.978497823","m15":"2047197.58783733","m30":"4074109.54013136","h1":"7911668.95957285","h6":"489476433.358862","h24":"489476433.358862"},"reserve_in_usd":"2147944.7692"},"relationships":{"base_token":{"data":{"id":"bsc_0xba760db451c9abcf7400f71b126e61b72d56507f","type":"token"}},"quote_token":{"data":{"id":"bsc_0x55d398326f99059ff775485246999027b3197955","type":"token"}},"dex":{"data":{"id":"pancakeswap_v2","type":"dex"}}}},{"id":"bsc_0x55fcae86ed8abe9c02470e9fbde5aca187b1fa5f","type":"pool","attributes":{"base_token_price_usd":"0.0000000000000000318478848692623","base_token_price_native_currency":"0.0000000000000000000619850467444939","quote_token_price_usd":"1.00120897655584","quote_token_price_native_currency":"0.00160096097821459","base_token_price_quote_token":"0.0000000000000000387174001","quote_token_price_base_token":"25828180541895000.0","address":"0x55fcae86ed8abe9c02470e9fbde5aca187b1fa5f","name":"AIGENSYN / USDT","pool_created_at":"2026-04-29T07:25:53Z","fdv_usd":"0.00000003184788487","market_cap_usd":null,"price_change_percentage":{"m5":"0","m15":"0","m30":"0","h1":"0","h6":"-100","h24":"-100"},"transactions":{"m5":{"buys":0,"sells":0,"buyers":0,"sellers":0},"m15":{"buys":0,"sells":0,"buyers":0,"sellers":0},"m30":{"buys":0,"sells":0,"buyers":0,"sellers":0},"h1":{"buys":0,"sells":0,"buyers":0,"sellers":0},"h6":{"buys":831,"sells":785,"buyers":601,"sellers":556},"h24":{"buys":831,"sells":785,"buyers":601,"sellers":556}},"volume_usd":{"m5":"0.0","m15":"0.0","m30":"0.0","h1":"0.0","h6":"471919184.684909","h24":"471919184.684909"},"reserve_in_usd":"0.0623"},"relationships":{"base_token":{"data":{"id":"bsc_0x75f18f43d8a148fccca9f4fdb332e21254065f4c","type":"token"}},"quote_token":{"data":{"id":"bsc_0x55d398326f99059ff775485246999027b3197955","type":"token"}},"dex":{"data":{"id":"pancakeswap_v2","type":"dex"}}}},{"id":"bsc_0x590182cb5e0db015345d406c90c0168f8d9df889","type":"pool","attributes":{"base_token_price_usd":"0.000000000000000117834951615492","base_token_price_native_currency":"0.000000000000000000571514585922799","quote_token_price_usd":"1.00359109867035","quote_token_price_native_currency":"0.00160506847624334","base_token_price_quote_token":"0.0000000000000003560686627","quote_token_price_base_token":"2808447090902690.0","address":"0x590182cb5e0db015345d406c90c0168f8d9df889","name":"AIGENSYN / USDT","pool_created_at":"2026-04-29T08:44:21Z","fdv_usd":"0.0000001177760341","market_cap_usd":null,"price_change_percentage":{"m5":"0","m15":"0","m30":"0","h1":"0","h6":"-100","h24":"-100"},"transactions":{"m5":{"buys":0,"sells":0,"buyers":0,"sellers":0},"m15":{"buys":0,"sells":0,"buyers":0,"sellers":0},"m30":{"buys":0,"sells":0,"buyers":0,"sellers":0},"h1":{"buys":0,"sells":0,"buyers":0,"sellers":0},"h6":{"buys":234,"sells":232,"buyers":5,"sellers":3},"h24":{"buys":234,"sells":232,"buyers":5,"sellers":3}},"volume_usd":{"m5":"0.0","m15":"0.0","m30":"0.0","h1":"0.0","h6":"462001627.908903","h24":"462001627.908903"},"reserve_in_usd":"0.1246"},"relationships":{"base_token":{"data":{"id":"bsc_0x03b969516f7788934d368f6b1b4a5f0f57a74e8c","type":"token"}},"quote_token":{"data":{"id":"bsc_0x55d398326f99059ff775485246999027b3197955","type":"token"}},"dex":{"data":{"id":"pancakeswap_v2","type":"dex"}}}},{"id":"bsc_0x5bf5dc59a4d9fc885f618afec1db77ebebf0cc1e","type":"pool","attributes":{"base_token_price_usd":"0.000000000000000117625594269791","base_token_price_native_currency":"0.000000000000000000571654741445603","quote_token_price_usd":"1.00358849956229","quote_token_price_native_currency":"0.00160438108414032","base_token_price_quote_token":"0.0000000000000003563085772","quote_token_price_base_token":"2806556069286080.0","address":"0x5bf5dc59a4d9fc885f618afec1db77ebebf0cc1e","name":"AI / USDT","pool_created_at":"2026-04-29T09:09:26Z","fdv_usd":"0.0000001175667815","market_cap_usd":null,"price_change_percentage":{"m5":"0","m15":"0","m30":"0","h1":"0","h6":"-100","h24":"-100"},"transactions":{"m5":{"buys":0,"sells":0,"buyers":0,"sellers":0},"m15":{"buys":0,"sells":0,"buyers":0,"sellers":0},"m30":{"buys":0,"sells":0,"buyers":0,"sellers":0},"h1":{"buys":0,"sells":0,"buyers":0,"sellers":0},"h6":{"buys":485,"sells":491,"buyers":256,"sellers":262},"h24":{"buys":485,"sells":491,"buyers":256,"sellers":262}},"volume_usd":{"m5":"0.0","m15":"0.0","m30":"0.0","h1":"0.0","h6":"460342709.535626","h24":"460342709.535626"},"reserve_in_usd":"0.1246"},"relationships":{"base_token":{"data":{"id":"bsc_0xb1a015b278b5960b712fc4e2591896f21c3d08bc","type":"token"}},"quote_token":{"data":{"id":"bsc_0x55d398326f99059ff775485246999027b3197955","type":"token"}},"dex":{"data":{"id":"pancakeswap_v2","type":"dex"}}}},{"id":"bsc_0xe1acb466421ed24dd8bd381d1205bad0ad43ca9c","type":"pool","attributes":{"base_token_price_usd":"0.00244351969576261","base_token_price_native_currency":"0.0000039179209116629632035742506736","quote_token_price_usd":"0.997934667914138","quote_token_price_native_currency":"0.0015999209092156","base_token_price_quote_token":"0.002448821619","quote_token_price_base_token":"408.3596747583","address":"0xe1acb466421ed24dd8bd381d1205bad0ad43ca9c","name":"quq / USDT 0.01%","pool_created_at":"2025-06-29T02:46:05Z","fdv_usd":"1937908.5851064","market_cap_usd":"2442810.519","price_change_percentage":{"m5":"0.032","m15":"0.011","m30":"0.135","h1":"0.137","h6":"0.01","h24":"-0.134"},"transactions":{"m5":{"buys":382,"sells":423,"buyers":104,"sellers":129},"m15":{"buys":1095,"sells":1186,"buyers":226,"sellers":283},"m30":{"buys":2179,"sells":2396,"buyers":385,"sellers":502},"h1":{"buys":4296,"sells":4759,"buyers":658,"sellers":839},"h6":{"buys":16023,"sells":16915,"buyers":1740,"sellers":1996},"h24":{"buys":67989,"sells":70791,"buyers":9542,"sellers":10017}},"volume_usd":{"m5":"2030366.79029114","m15":"6061668.20533268","m30":"13539368.1628262","h1":"25008696.0130882","h6":"99763768.6466506","h24":"377351739.213719"},"reserve_in_usd":"2805343.4374"},"relationships":{"base_token":{"data":{"id":"bsc_0x4fa7c69a7b69f8bc48233024d546bc299d6b03bf","type":"token"}},"quote_token":{"data":{"id":"bsc_0x55d398326f99059ff775485246999027b3197955","type":"token"}},"dex":{"data":{"id":"uniswap-bsc","type":"dex"}}}},{"id":"bsc_0xb8021d3fc12b8653f1beef1c8763dc993882590a","type":"pool","attributes":{"base_token_price_usd":"0.0000000000000000314031202599574","base_token_price_native_currency":"0.0000000000000000000618797403345554","quote_token_price_usd":"1.00160860268974","quote_token_price_native_currency":"0.00160108795468164","base_token_price_quote_token":"0.00000000000000003864855778","quote_token_price_base_token":"25874186705136300.0","address":"0xb8021d3fc12b8653f1beef1c8763dc993882590a","name":"SCAM / USDT","pool_created_at":"2026-04-28T06:47:41Z","fdv_usd":"0.0000000313874187","market_cap_usd":null,"price_change_percentage":{"m5":"0","m15":"0","m30":"0","h1":"0","h6":"-100","h24":"-100"},"transactions":{"m5":{"buys":0,"sells":0,"buyers":0,"sellers":0},"m15":{"buys":0,"sells":0,"buyers":0,"sellers":0},"m30":{"buys":0,"sells":0,"buyers":0,"sellers":0},"h1":{"buys":0,"sells":0,"buyers":0,"sellers":0},"h6":{"buys":214,"sells":207,"buyers":214,"sellers":207},"h24":{"buys":4987,"sells":4982,"buyers":3755,"sellers":3752}},"volume_usd":{"m5":"0.0","m15":"0.0","m30":"0.0","h1":"0.0","h6":"7603597.22774765","h24":"149130414.742373"},"reserve_in_usd":"0.0623"},"relationships":{"base_token":{"data":{"id":"bsc_0x76c974f967e8a9d7026ea4c327e103d2d302b825","type":"token"}},"quote_token":{"data":{"id":"bsc_0x55d398326f99059ff775485246999027b3197955","type":"token"}},"dex":{"data":{"id":"pancakeswap_v2","type":"dex"}}}},{"id":"bsc_0x1c09de1171ae2d743cfdfa94c12e311539cd0b98","type":"pool","attributes":{"base_token_price_usd":"0.0689851164192837","base_token_price_native_currency":"0.000114595482344111","quote_token_price_usd":"623.74","quote_token_price_native_currency":"1.0","base_token_price_quote_token":"0.0001145954823","quote_token_price_base_token":"8726.347492453","address":"0x1c09de1171ae2d743cfdfa94c12e311539cd0b98","name":"ASTEROID / WBNB","pool_created_at":"2026-04-29T04:52:24Z","fdv_usd":"7083976175.0","market_cap_usd":null,"price_change_percentage":{"m5":"19.069","m15":"19.326","m30":"292.899","h1":"416.733","h6":"262.726","h24":"22561777568.585"},"transactions":{"m5":{"buys":16,"sells":3,"buyers":8,"sellers":2},"m15":{"buys":42,"sells":13,"buyers":17,"sellers":3},"m30":{"buys":86,"sells":25,"buyers":31,"sellers":3},"h1":{"buys":168,"sells":54,"buyers":58,"sellers":3},"h6":{"buys":1003,"sells":327,"buyers":318,"sellers":3},"h24":{"buys":2675,"sells":1703,"buyers":463,"sellers":4}},"volume_usd":{"m5":"8573.7805471438","m15":"26619.1055206938","m30":"62332.9895712932","h1":"111713.079840841","h6":"878055.011584364","h24":"96118461.5772837"},"reserve_in_usd":"88058.9658"},"relationships":{"base_token":{"data":{"id":"bsc_0x6397a09d0244fff2d970c2e3ffdee60018db1a9b","type":"token"}},"quote_token":{"data":{"id":"bsc_0xbb4cdb9cbd36b01bd1cbaebf2de08d9173bc095c","type":"token"}},"dex":{"data":{"id":"pancakeswap_v2","type":"dex"}}}},{"id":"bsc_0xc8d9e68f6f933f198010116efbfca19f82e4bd37","type":"pool","attributes":{"base_token_price_usd":"0.0000068805110212843","base_token_price_native_currency":"0.000000011003357216186","quote_token_price_usd":"623.74","quote_token_price_native_currency":"1.0","base_token_price_quote_token":"0.00000001100335722","quote_token_price_base_token":"90881353.7861876","address":"0xc8d9e68f6f933f198010116efbfca19f82e4bd37","name":"SCAM / WBNB","pool_created_at":"2026-04-29T04:28:26Z","fdv_usd":"6852829550.0","market_cap_usd":null,"price_change_percentage":{"m5":"-7.694","m15":"-6.777","m30":"4.078","h1":"2.383","h6":"385.775","h24":"109504628322.07"},"transactions":{"m5":{"buys":9,"sells":5,"buyers":2,"sellers":1},"m15":{"buys":26,"sells":13,"buyers":7,"sellers":1},"m30":{"buys":53,"sells":24,"buyers":14,"sellers":1},"h1":{"buys":103,"sells":50,"buyers":25,"sellers":1},"h6":{"buys":596,"sells":277,"buyers":110,"sellers":1},"h24":{"buys":2065,"sells":1575,"buyers":151,"sellers":2}},"volume_usd":{"m5":"4992.9263746892","m15":"13539.0990788787","m30":"25856.0972956152","h1":"57070.940562177","h6":"337619.370909609","h24":"71347560.2797736"},"reserve_in_usd":"102711.4314"},"relationships":{"base_token":{"data":{"id":"bsc_0x8df6ad242318855c5e8fce7b706bda44715839ca","type":"token"}},"quote_token":{"data":{"id":"bsc_0xbb4cdb9cbd36b01bd1cbaebf2de08d9173bc095c","type":"token"}},"dex":{"data":{"id":"pancakeswap_v2","type":"dex"}}}},{"id":"bsc_0x172fcd41e0913e95784454622d1c3724f546f849","type":"pool","attributes":{"base_token_price_usd":"0.999634031270977","base_token_price_native_currency":"0.0015999209092156","quote_token_price_usd":"623.74","quote_token_price_native_currency":"1.0","base_token_price_quote_token":"0.001599920909","quote_token_price_base_token":"625.030896365","address":"0x172fcd41e0913e95784454622d1c3724f546f849","name":"USDT / WBNB 0.01%","pool_created_at":"2025-11-09T12:44:04Z","fdv_usd":"9179298035.36248","market_cap_usd":"9179595255.04295","price_change_percentage":{"m5":"-0.077","m15":"-0.048","m30":"-0.061","h1":"-0.025","h6":"0.01","h24":"-0.064"},"transactions":{"m5":{"buys":364,"sells":625,"buyers":184,"sellers":256},"m15":{"buys":970,"sells":1623,"buyers":406,"sellers":526},"m30":{"buys":2015,"sells":3609,"buyers":698,"sellers":937},"h1":{"buys":4174,"sells":8201,"buyers":1206,"sellers":1739},"h6":{"buys":21425,"sells":37912,"buyers":4602,"sellers":5695},"h24":{"buys":76302,"sells":133983,"buyers":12474,"sellers":13658}},"volume_usd":{"m5":"382811.741123728","m15":"956560.353364539","m30":"2205773.95354581","h1":"5269979.71676796","h6":"20384307.4333867","h24":"64428746.4587572"},"reserve_in_usd":"17596372.7701"},"relationships":{"base_token":{"data":{"id":"bsc_0x55d398326f99059ff775485246999027b3197955","type":"token"}},"quote_token":{"data":{"id":"bsc_0xbb4cdb9cbd36b01bd1cbaebf2de08d9173bc095c","type":"token"}},"dex":{"data":{"id":"pancakeswap-v3-bsc","type":"dex"}}}},{"id":"bsc_0xb75a0c1ee0eb3be7e8aaf81f1bfe8f4f8d312438","type":"pool","attributes":{"base_token_price_usd":"0.00000187760175230631","base_token_price_native_currency":"0.00000000300525438986678","quote_token_price_usd":"626.1","quote_token_price_native_currency":"1.0","base_token_price_quote_token":"0.00000000300525439","quote_token_price_base_token":"332750532.99043","address":"0xb75a0c1ee0eb3be7e8aaf81f1bfe8f4f8d312438","name":"SH / WBNB","pool_created_at":"2025-12-10T08:43:43Z","fdv_usd":"39.429636792","market_cap_usd":null,"price_change_percentage":{"m5":"0","m15":"0","m30":"0","h1":"0","h6":"-100","h24":"-1.407"},"transactions":{"m5":{"buys":0,"sells":0,"buyers":0,"sellers":0},"m15":{"buys":0,"sells":0,"buyers":0,"sellers":0},"m30":{"buys":0,"sells":0,"buyers":0,"sellers":0},"h1":{"buys":0,"sells":0,"buyers":0,"sellers":0},"h6":{"buys":4,"sells":5,"buyers":3,"sellers":2},"h24":{"buys":4,"sells":8,"buyers":3,"sellers":2}},"volume_usd":{"m5":"0.0","m15":"0.0","m30":"0.0","h1":"0.0","h6":"62573000.0886559","h24":"62573000.0912135"},"reserve_in_usd":"6.5469"},"relationships":{"base_token":{"data":{"id":"bsc_0xda8d7b5f298ecaf396d6b8602ecbf8169002ee84","type":"token"}},"quote_token":{"data":{"id":"bsc_0xbb4cdb9cbd36b01bd1cbaebf2de08d9173bc095c","type":"token"}},"dex":{"data":{"id":"pancakeswap_v2","type":"dex"}}}},{"id":"bsc_0x364bf81c2879cb43e94fca54e6e9cad5053cba70","type":"pool","attributes":{"base_token_price_usd":"0.0000624962966064077","base_token_price_native_currency":"0.000000100280126230549","quote_token_price_usd":"0.997640573893815","quote_token_price_native_currency":"0.00160799314452411","base_token_price_quote_token":"0.00006236352846","quote_token_price_base_token":"16035.0131672875","address":"0x364bf81c2879cb43e94fca54e6e9cad5053cba70","name":"agentic money / USDT","pool_created_at":"2026-04-29T12:27:00Z","fdv_usd":"62563.56756","market_cap_usd":null,"price_change_percentage":{"m5":"10.47","m15":"27.747","m30":"3011.588","h1":"3011.588","h6":"3011.588","h24":"3011.588"},"transactions":{"m5":{"buys":39,"sells":0,"buyers":39,"sellers":0},"m15":{"buys":110,"sells":0,"buyers":110,"sellers":0},"m30":{"buys":1085,"sells":900,"buyers":186,"sellers":1},"h1":{"buys":1085,"sells":900,"buyers":186,"sellers":1},"h6":{"buys":1085,"sells":900,"buyers":186,"sellers":1},"h24":{"buys":1085,"sells":900,"buyers":186,"sellers":1}},"volume_usd":{"m5":"2608.2210182865","m15":"6101.3880268714","m30":"57015427.2707216","h1":"57015427.2707216","h6":"57015427.2707216","h24":"57015427.2707216"},"reserve_in_usd":"107075.0419"},"relationships":{"base_token":{"data":{"id":"bsc_0xdc723512c7ddbccdeb021ab88bf0db77b8844444","type":"token"}},"quote_token":{"data":{"id":"bsc_0x55d398326f99059ff775485246999027b3197955","type":"token"}},"dex":{"data":{"id":"pancakeswap_v2","type":"dex"}}}},{"id":"bsc_0xad8ed7e9ee20eddc960e9abecfb3caeccf1f65ab","type":"pool","attributes":{"base_token_price_usd":"5.6915848057314","base_token_price_native_currency":"0.00900778097470012","quote_token_price_usd":"0.997934667914138","quote_token_price_native_currency":"0.00160391644841952","base_token_price_quote_token":"5.6161160911","quote_token_price_base_token":"0.1780589973","address":"0xad8ed7e9ee20eddc960e9abecfb3caeccf1f65ab","name":"XChat / USDT","pool_created_at":"2026-04-28T07:45:33Z","fdv_usd":"60182730.452","market_cap_usd":null,"price_change_percentage":{"m5":"6.325","m15":"17.916","m30":"4.971","h1":"-5.026","h6":"59680.337","h24":"59680.337"},"transactions":{"m5":{"buys":96,"sells":6,"buyers":96,"sellers":3},"m15":{"buys":283,"sells":42,"buyers":282,"sellers":22},"m30":{"buys":580,"sells":114,"buyers":573,"sellers":57},"h1":{"buys":1189,"sells":182,"buyers":832,"sellers":80},"h6":{"buys":5418,"sells":828,"buyers":1448,"sellers":261},"h24":{"buys":5418,"sells":828,"buyers":1448,"sellers":261}},"volume_usd":{"m5":"105668.448354125","m15":"288535.65847472","m30":"630872.1892228","h1":"1328881.0455377","h6":"49810098.0369751","h24":"49810098.0369751"},"reserve_in_usd":"1095904.7046"},"relationships":{"base_token":{"data":{"id":"bsc_0x749f341963eb5001c56a92eebae4ddc0f97f8411","type":"token"}},"quote_token":{"data":{"id":"bsc_0x55d398326f99059ff775485246999027b3197955","type":"token"}},"dex":{"data":{"id":"pancakeswap_v2","type":"dex"}}}},{"id":"bsc_0x101552cfd9d16f17db7d11fde6082e4671e9fe39cb21679bb3fad5be9e5ec2c9","type":"pool","attributes":{"base_token_price_usd":"0.800542703910843","base_token_price_native_currency":"0.00129114593217876","quote_token_price_usd":"0.997646682150479","quote_token_price_native_currency":"0.00160393398849548","base_token_price_quote_token":"0.8049869517","quote_token_price_base_token":"1.2422561606","address":"0x101552cfd9d16f17db7d11fde6082e4671e9fe39cb21679bb3fad5be9e5ec2c9","name":"RAVE / USDT 0.007%","pool_created_at":"2025-12-11T04:28:55Z","fdv_usd":"26785444.9196019","market_cap_usd":"199149765.888934","price_change_percentage":{"m5":"0.551","m15":"-0.053","m30":"-0.622","h1":"0.758","h6":"-4.167","h24":"-8.221"},"transactions":{"m5":{"buys":55,"sells":53,"buyers":36,"sellers":33},"m15":{"buys":240,"sells":231,"buyers":94,"sellers":102},"m30":{"buys":519,"sells":509,"buyers":176,"sellers":185},"h1":{"buys":1278,"sells":1268,"buyers":361,"sellers":359},"h6":{"buys":5767,"sells":5500,"buyers":1110,"sellers":1177},"h24":{"buys":47552,"sells":47608,"buyers":5155,"sellers":5295}},"volume_usd":{"m5":"25165.6452280917","m15":"130965.221902408","m30":"275520.382138155","h1":"725519.015105429","h6":"3159336.8551007","h24":"27808301.0989334"},"reserve_in_usd":"1964912.9484"},"relationships":{"base_token":{"data":{"id":"bsc_0x97693439ea2f0ecdeb9135881e49f354656a911c","type":"token"}},"quote_token":{"data":{"id":"bsc_0x55d398326f99059ff775485246999027b3197955","type":"token"}},"dex":{"data":{"id":"pancakeswap-infinity-clmm","type":"dex"}}}},{"id":"bsc_0xbc42145d5a574ede9b8860fca2a49eb7b239efa5","type":"pool","attributes":{"base_token_price_usd":"0.24734309146656","base_token_price_native_currency":"0.000395663414210692","quote_token_price_usd":"623.56","quote_token_price_native_currency":"1.0","base_token_price_quote_token":"0.0003956634142","quote_token_price_base_token":"2527.400725172","address":"0xbc42145d5a574ede9b8860fca2a49eb7b239efa5","name":"SKYAI / WBNB","pool_created_at":"2025-04-20T03:42:03Z","fdv_usd":"242252486.821547","market_cap_usd":"242252486.821547","price_change_percentage":{"m5":"-0.063","m15":"-6.024","m30":"-0.92","h1":"-11.902","h6":"6.441","h24":"53.044"},"transactions":{"m5":{"buys":163,"sells":215,"buyers":99,"sellers":97},"m15":{"buys":449,"sells":674,"buyers":200,"sellers":204},"m30":{"buys":1212,"sells":1293,"buyers":328,"sellers":333},"h1":{"buys":2497,"sells":2479,"buyers":463,"sellers":478},"h6":{"buys":6512,"sells":5074,"buyers":842,"sellers":763},"h24":{"buys":20914,"sells":14436,"buyers":1173,"sellers":1229}},"volume_usd":{"m5":"317244.957570532","m15":"888414.150534505","m30":"2115369.37349531","h1":"4132794.96720737","h6":"8223575.24510467","h24":"20589086.9413057"},"reserve_in_usd":"10307243.5194"},"relationships":{"base_token":{"data":{"id":"bsc_0x92aa03137385f18539301349dcfc9ebc923ffb10","type":"token"}},"quote_token":{"data":{"id":"bsc_0xbb4cdb9cbd36b01bd1cbaebf2de08d9173bc095c","type":"token"}},"dex":{"data":{"id":"pancakeswap_v2","type":"dex"}}}},{"id":"bsc_0x4177d01a5b15438438f4e9f19a6015eed58f708f","type":"pool","attributes":{"base_token_price_usd":"0.00244807317674743","base_token_price_native_currency":"0.00000391520057248563","quote_token_price_usd":"0.999529314257997","quote_token_price_native_currency":"0.00160247749744765","base_token_price_quote_token":"0.002443217193","quote_token_price_base_token":"409.2963994512","address":"0x4177d01a5b15438438f4e9f19a6015eed58f708f","name":"quq / USDC 0.01%","pool_created_at":"2025-07-06T09:15:00Z","fdv_usd":"1941140.49308414","market_cap_usd":"2446884.467","price_change_percentage":{"m5":"-0.068","m15":"-0.064","m30":"-0.077","h1":"-0.066","h6":"-0.009","h24":"-0.035"},"transactions":{"m5":{"buys":301,"sells":284,"buyers":63,"sellers":66},"m15":{"buys":760,"sells":719,"buyers":143,"sellers":164},"m30":{"buys":1442,"sells":1424,"buyers":265,"sellers":336},"h1":{"buys":2828,"sells":2791,"buyers":466,"sellers":572},"h6":{"buys":6142,"sells":6121,"buyers":1049,"sellers":1173},"h24":{"buys":40002,"sells":40568,"buyers":7603,"sellers":7749}},"volume_usd":{"m5":"109939.43502852","m15":"311664.411378038","m30":"614983.641041376","h1":"1124690.85571087","h6":"2577246.65527966","h24":"19030471.0711499"},"reserve_in_usd":"118020.2035"},"relationships":{"base_token":{"data":{"id":"bsc_0x4fa7c69a7b69f8bc48233024d546bc299d6b03bf","type":"token"}},"quote_token":{"data":{"id":"bsc_0x8ac76a51cc950d9822d68b83fe1ad97b32cd580d","type":"token"}},"dex":{"data":{"id":"pancakeswap-v3-bsc","type":"dex"}}}},{"id":"bsc_0xb433ae7e7011a2fb9a4bbb86140e0f653dcfcfba","type":"pool","attributes":{"base_token_price_usd":"0.0998873285077069","base_token_price_native_currency":"0.000159845457369691","quote_token_price_usd":"623.74","quote_token_price_native_currency":"1.0","base_token_price_quote_token":"0.0001598454574","quote_token_price_base_token":"6256.042658048","address":"0xb433ae7e7011a2fb9a4bbb86140e0f653dcfcfba","name":"AIOT / WBNB 0.01%","pool_created_at":"2025-04-29T10:56:18Z","fdv_usd":"99611611.1398433","market_cap_usd":"26222766.5937661","price_change_percentage":{"m5":"-0.668","m15":"-1.897","m30":"-7.394","h1":"3.648","h6":"9.208","h24":"20.392"},"transactions":{"m5":{"buys":311,"sells":289,"buyers":146,"sellers":154},"m15":{"buys":892,"sells":878,"buyers":283,"sellers":278},"m30":{"buys":2139,"sells":2143,"buyers":496,"sellers":475},"h1":{"buys":5284,"sells":5680,"buyers":875,"sellers":773},"h6":{"buys":23722,"sells":25326,"buyers":1759,"sellers":1805},"h24":{"buys":82702,"sells":87568,"buyers":3059,"sellers":2966}},"volume_usd":{"m5":"43585.9648538273","m15":"129986.617656014","m30":"336364.567297049","h1":"932315.322086146","h6":"4421289.04809781","h24":"15409739.3324338"},"reserve_in_usd":"2852711.2375"},"relationships":{"base_token":{"data":{"id":"bsc_0x55ad16bd573b3365f43a9daeb0cc66a73821b4a5","type":"token"}},"quote_token":{"data":{"id":"bsc_0xbb4cdb9cbd36b01bd1cbaebf2de08d9173bc095c","type":"token"}},"dex":{"data":{"id":"pancakeswap-v3-bsc","type":"dex"}}}},{"id":"bsc_0x157f51edede49476dce22a3442d33d5752fc207541fd36f5904f4bded4d2769c","type":"pool","attributes":{"base_token_price_usd":"0.24988564713939","base_token_price_native_currency":"0.00040067421680836","quote_token_price_usd":"0.997806971686159","quote_token_price_native_currency":"0.00159997269528279","base_token_price_quote_token":"0.2504256591","quote_token_price_base_token":"3.9932010301","address":"0x157f51edede49476dce22a3442d33d5752fc207541fd36f5904f4bded4d2769c","name":"ARTX / USDT 0.007%","pool_created_at":"2025-11-20T09:12:05Z","fdv_usd":"20595442.3985073","market_cap_usd":null,"price_change_percentage":{"m5":"0.173","m15":"-0.148","m30":"0.21","h1":"0.006","h6":"2.632","h24":"1.437"},"transactions":{"m5":{"buys":13,"sells":19,"buyers":9,"sellers":13},"m15":{"buys":30,"sells":33,"buyers":21,"sellers":24},"m30":{"buys":74,"sells":72,"buyers":58,"sellers":57},"h1":{"buys":253,"sells":249,"buyers":165,"sellers":170},"h6":{"buys":2387,"sells":2305,"buyers":332,"sellers":314},"h24":{"buys":8458,"sells":8467,"buyers":548,"sellers":526}},"volume_usd":{"m5":"18006.7257321546","m15":"42345.3435964164","m30":"117481.378488387","h1":"515953.619722404","h6":"4382381.8220595","h24":"14724304.2222594"},"reserve_in_usd":"1661280.2587"},"relationships":{"base_token":{"data":{"id":"bsc_0x8105743e8a19c915a604d7d9e7aa3a060a4c2c32","type":"token"}},"quote_token":{"data":{"id":"bsc_0x55d398326f99059ff775485246999027b3197955","type":"token"}},"dex":{"data":{"id":"pancakeswap-infinity-clmm","type":"dex"}}}},{"id":"bsc_0xb428f9ab060a8381add435701ecf58af7f75f317e5d76a939fc03918158df44d","type":"pool","attributes":{"base_token_price_usd":"0.00360551292910606","base_token_price_native_currency":"0.00000579290933905152","quote_token_price_usd":"0.997646682150479","quote_token_price_native_currency":"0.0015999209092156","base_token_price_quote_token":"0.003620747317","quote_token_price_base_token":"276.1860777675","address":"0xb428f9ab060a8381add435701ecf58af7f75f317e5d76a939fc03918158df44d","name":"JCT / USDT 0.007%","pool_created_at":"2025-11-09T08:17:52Z","fdv_usd":"23010173.0096085","market_cap_usd":"41776777.0381821","price_change_percentage":{"m5":"-0.559","m15":"-4.385","m30":"-3.179","h1":"-1.6","h6":"-0.636","h24":"16.916"},"transactions":{"m5":{"buys":298,"sells":356,"buyers":161,"sellers":150},"m15":{"buys":1036,"sells":1181,"buyers":315,"sellers":287},"m30":{"buys":1943,"sells":2197,"buyers":422,"sellers":404},"h1":{"buys":3579,"sells":4067,"buyers":499,"sellers":504},"h6":{"buys":11390,"sells":12768,"buyers":650,"sellers":656},"h24":{"buys":34859,"sells":37720,"buyers":1247,"sellers":1328}},"volume_usd":{"m5":"122596.603006644","m15":"432308.802117607","m30":"806693.928476935","h1":"1495898.16784062","h6":"4560749.32208276","h24":"13112297.549723"},"reserve_in_usd":"842065.2762"},"relationships":{"base_token":{"data":{"id":"bsc_0xea37a8de1de2d9d10772eeb569e28bfa5cb17707","type":"token"}},"quote_token":{"data":{"id":"bsc_0x55d398326f99059ff775485246999027b3197955","type":"token"}},"dex":{"data":{"id":"pancakeswap-infinity-clmm","type":"dex"}}}},{"id":"bsc_0x017bcd5ce750c39cf81f24f57fd86134e226e623","type":"pool","attributes":{"base_token_price_usd":"0.00480720278758257","base_token_price_native_currency":"0.0000076964077079399","quote_token_price_usd":"0.999069497712552","quote_token_price_native_currency":"0.00159618714785281","base_token_price_quote_token":"0.004821745193","quote_token_price_base_token":"207.3937879104","address":"0x017bcd5ce750c39cf81f24f57fd86134e226e623","name":"GLCS / USDT","pool_created_at":"2024-03-09T03:28:28Z","fdv_usd":"5008.2871477832","market_cap_usd":null,"price_change_percentage":{"m5":"0","m15":"0","m30":"0","h1":"0","h6":"0.566","h24":"2.193"},"transactions":{"m5":{"buys":0,"sells":0,"buyers":0,"sellers":0},"m15":{"buys":0,"sells":0,"buyers":0,"sellers":0},"m30":{"buys":0,"sells":0,"buyers":0,"sellers":0},"h1":{"buys":0,"sells":0,"buyers":0,"sellers":0},"h6":{"buys":1,"sells":2,"buyers":1,"sellers":2},"h24":{"buys":2,"sells":5,"buyers":2,"sellers":4}},"volume_usd":{"m5":"0.0","m15":"0.0","m30":"0.0","h1":"0.0","h6":"6.203725883","h24":"12828404.1320399"},"reserve_in_usd":"1617.1678"},"relationships":{"base_token":{"data":{"id":"bsc_0x65a4fb74ced27d141dc6a8fcdcb737d35e8f453e","type":"token"}},"quote_token":{"data":{"id":"bsc_0x55d398326f99059ff775485246999027b3197955","type":"token"}},"dex":{"data":{"id":"pancakeswap_v2","type":"dex"}}}},{"id":"bsc_0x628ea54a6450645d2bb7b2911c8c6f3d7f3944c2f4703c259a1b85bf5569870b","type":"pool","attributes":{"base_token_price_usd":"0.997646682150479","base_token_price_native_currency":"0.0015999209092156","quote_token_price_usd":"0.999240868308457","quote_token_price_native_currency":"0.00160247749744765","base_token_price_quote_token":"0.9984046027","quote_token_price_base_token":"1.0015979466","address":"0x628ea54a6450645d2bb7b2911c8c6f3d7f3944c2f4703c259a1b85bf5569870b","name":"USDT / USDC","pool_created_at":"2025-08-05T16:13:57Z","fdv_usd":"9163080740.2028","market_cap_usd":"9163377434.77784","price_change_percentage":{"m5":"-0.466","m15":"0.017","m30":"0.135","h1":"-0.351","h6":"-0.012","h24":"-0.151"},"transactions":{"m5":{"buys":80,"sells":68,"buyers":72,"sellers":59},"m15":{"buys":212,"sells":158,"buyers":177,"sellers":134},"m30":{"buys":431,"sells":335,"buyers":335,"sellers":272},"h1":{"buys":897,"sells":631,"buyers":624,"sellers":470},"h6":{"buys":3222,"sells":2938,"buyers":1694,"sellers":1575},"h24":{"buys":14579,"sells":14184,"buyers":6064,"sellers":5828}},"volume_usd":{"m5":"90313.6624397646","m15":"168609.008694998","m30":"345487.959567275","h1":"581610.828694452","h6":"2367597.71991522","h24":"12688855.8598981"},"reserve_in_usd":"367668.9345"},"relationships":{"base_token":{"data":{"id":"bsc_0x55d398326f99059ff775485246999027b3197955","type":"token"}},"quote_token":{"data":{"id":"bsc_0x8ac76a51cc950d9822d68b83fe1ad97b32cd580d","type":"token"}},"dex":{"data":{"id":"uniswap-v4-bsc","type":"dex"}}}}]}